{
  "schema_version": "stella.article_data_assets.extraction.v2",
  "generated_at": "2026-05-17T20:08:02",
  "paper": {
    "arxiv_id": "2407.09934",
    "title": "The runaway nature and origin of {\\alpha} Crucis system",
    "month": "2024-07"
  },
  "review": {
    "path": "literature/2407.09934/catalog_review.json",
    "schema_version": "stella.article_data_assets.review.v1",
    "review_status": "reviewed"
  },
  "run": {
    "run_id": "catalog-extraction-20260517T200802",
    "started_at": "2026-05-17T20:08:02",
    "tool": "scripts/extract_catalog_tables.py",
    "options": {
      "arxiv_id": "2407.09934",
      "internal_table_id": null,
      "dry_run": false,
      "overwrite": false
    },
    "summary": {
      "internal_table_count": 0,
      "work_count": 0,
      "table_count": 0,
      "success_count": 0,
      "failed_count": 0,
      "deferred_count": 0,
      "file_count": 0,
      "file_success_count": 0,
      "file_failed_count": 0
    },
    "status": "skipped"
  },
  "files": [],
  "tables": []
}
