{
  "schema_version": "stella.article_data_assets.review.v0.1",
  "paper": {
    "arxiv_id": "2011.10206",
    "title": "591 high velocity stars in the Galactic halo selected from LAMOST DR7 and Gaia DR2",
    "month": "2020-11",
    "source_note_json": "notes/2020/2020-11/2020-11.json",
    "links": {
      "abs": "https://arxiv.org/abs/2011.10206",
      "pdf": "https://arxiv.org/pdf/2011.10206"
    }
  },
  "source": {
    "paper_dir": "literature/2011.10206",
    "audit_path": "literature/2011.10206/audit.json",
    "source_dir": "literature/2011.10206/arxiv_source",
    "tex_root": "literature/2011.10206/arxiv_source/LAMOST_II_HVS.tex",
    "source_available": true
  },
  "review": {
    "status": "reviewed",
    "reviewed_at": "2026-06-06T22:37:14",
    "reviewer": "agent",
    "summary": "This ApJS paper presents a catalog of 591 high-velocity star candidates selected from LAMOST DR7 and Gaia DR2. The LaTeX source contains nine tables (mostly deluxetable* inside longrotatetable environments), four of which are in the main text (tab:basic, tab:kinematic, tab:punbound_50, tab:origin, tab:strict_criteria) and four in the appendix (tab:vesc, tab:unbound, tab:atmospheric, tab:general_catalog). The primary data asset is an external CSV catalog hosted at http://paperdata.china-vo.org/LYB/lamostdr7_gaiadr2_hvs_591.csv containing 93 columns for all 591 candidates. Additionally, the paper references the Open Fast Stars Catalog at https://faststars.space/ and survey/tool URLs (LAMOST DR5/DR7, TOPCAT). The appendix also includes a longtable (tab:general_catalog) documenting all 93 columns of the external catalog."
  },
  "internal_tables": [
    {
      "id": "table-001",
      "kind": "latex_table",
      "asset_type": "object_measurement_table",
      "role_in_paper": "Tab:basic — Basic parameters (R.A., decl., S/N, spectral type, RV, proper motions, parallax, Gaia magnitudes, astrometric flag) for the 20 fastest HiVelSCs.",
      "source_refs": [
        {
          "path": "literature/2011.10206/arxiv_source/LAMOST_II_HVS.tex",
          "start_line": 308,
          "end_line": 374,
          "caption": "Basic parameters for the 20 fastest High velocity star candidates (HiVelSCs)",
          "label": "tab:basic"
        }
      ],
      "columns": [
        {
          "name": "ID",
          "meaning": "High velocity star identifier (Hivel1–Hivel20)"
        },
        {
          "name": "R.A.",
          "meaning": "Right ascension (deg)"
        },
        {
          "name": "decl.",
          "meaning": "Declination (deg)"
        },
        {
          "name": "S/N_r",
          "meaning": "r-band spectral signal-to-noise ratio from LAMOST"
        },
        {
          "name": "Class",
          "meaning": "Spectral type from LAMOST 1D pipeline"
        },
        {
          "name": "RV_LASP",
          "meaning": "Radial velocity from LASP, zero-point corrected (km/s)"
        },
        {
          "name": "pmra",
          "meaning": "Proper motion in right ascension from Gaia DR2 (mas/yr)"
        },
        {
          "name": "pmdec",
          "meaning": "Proper motion in declination from Gaia DR2 (mas/yr)"
        },
        {
          "name": "parallax",
          "meaning": "Parallax from Gaia DR2 (mas)"
        },
        {
          "name": "G",
          "meaning": "Gaia G-band mean magnitude (mag)"
        },
        {
          "name": "G_BP",
          "meaning": "Gaia BP-band mean magnitude (mag)"
        },
        {
          "name": "G_RP",
          "meaning": "Gaia RP-band mean magnitude (mag)"
        },
        {
          "name": "astrometric_flag",
          "meaning": "Flag (=1) if astrometric parameters meet conservative quality criteria"
        }
      ],
      "evidence": "Table in Section 2.4 lists observed and derived basic parameters for the 20 fastest HiVelSCs, with footnotes explaining column provenance.",
      "comments": "Only the 20 fastest candidates shown in print; full 591-row catalog is external (CSV)."
    },
    {
      "id": "table-002",
      "kind": "latex_table",
      "asset_type": "object_measurement_table",
      "role_in_paper": "Tab:kinematic — Galactocentric spatial positions (x, y, z), distance, velocities (Vx, Vy, Vz, V_GC), and orbit parameters (e, Zmax, rmin, E-Phi) for the 20 fastest HiVelSCs.",
      "source_refs": [
        {
          "path": "literature/2011.10206/arxiv_source/LAMOST_II_HVS.tex",
          "start_line": 376,
          "end_line": 433,
          "caption": "Spatial Positions and Velocities of the 20 fastest HiVelSCs",
          "label": "tab:kinematic"
        }
      ],
      "columns": [
        {
          "name": "ID",
          "meaning": "High velocity star identifier"
        },
        {
          "name": "x",
          "meaning": "Galactocentric Cartesian x coordinate (kpc)"
        },
        {
          "name": "y",
          "meaning": "Galactocentric Cartesian y coordinate (kpc)"
        },
        {
          "name": "z",
          "meaning": "Galactocentric Cartesian z coordinate (kpc)"
        },
        {
          "name": "r_GC",
          "meaning": "Galactocentric distance (kpc)"
        },
        {
          "name": "Vx",
          "meaning": "Galactocentric x velocity (km/s)"
        },
        {
          "name": "Vy",
          "meaning": "Galactocentric y velocity (km/s)"
        },
        {
          "name": "Vz",
          "meaning": "Galactocentric z velocity (km/s)"
        },
        {
          "name": "V_GC",
          "meaning": "Galactocentric total velocity (km/s)"
        },
        {
          "name": "e",
          "meaning": "Orbit eccentricity"
        },
        {
          "name": "Zmax",
          "meaning": "Orbital maximum height above Galactic disk (kpc)"
        },
        {
          "name": "rmin",
          "meaning": "Minimum crossing radius during orbital trace-back (kpc)"
        },
        {
          "name": "E-Phi(inf)",
          "meaning": "Energy difference between orbital energy and potential at infinity (kpc^2/Myr^2)"
        }
      ],
      "evidence": "Table in Section 2.4 presents derived kinematic and orbital parameters from Monte Carlo sampling of astrometry and seven Galactic potential models.",
      "comments": "Only 20 fastest shown; bound/unbound status and orbit parameters for full sample in external CSV."
    },
    {
      "id": "table-003",
      "kind": "latex_table",
      "asset_type": "summary_table",
      "role_in_paper": "Tab:punbound_50 — Number of HiVelSCs with unbound probability >50% under each of seven Galactic potential models.",
      "source_refs": [
        {
          "path": "literature/2011.10206/arxiv_source/LAMOST_II_HVS.tex",
          "start_line": 487,
          "end_line": 497,
          "caption": "The number of HiVelSCs with probabilities of being unbound larger than 50% in each of the seven potential models",
          "label": "tab:punbound_50"
        }
      ],
      "columns": [
        {
          "name": "Model",
          "meaning": "Galactic potential model (Watkins+2019, Gnedin+2005, Kenyon+2014, Koposov+2010, Paczynski+1990, MWPotential2014, Xue+2008)"
        },
        {
          "name": "N(Pub>=50%)",
          "meaning": "Number of HiVelSCs with unbound probability ≥50%"
        }
      ],
      "evidence": "Table in Section 2.4 summarizes unbound candidate counts across seven potential models, ranging from 43 (Watkins+2019) to 304 (Xue+2008).",
      "comments": "Single-row summary table."
    },
    {
      "id": "table-004",
      "kind": "latex_table",
      "asset_type": "classification_schema",
      "role_in_paper": "Tab:origin — Classification criteria dividing HiVelSCs into HVS, HRS, RS, and OUT types based on Pgc, PMW, and Pub thresholds.",
      "source_refs": [
        {
          "path": "literature/2011.10206/arxiv_source/LAMOST_II_HVS.tex",
          "start_line": 709,
          "end_line": 722,
          "caption": "The classification criteria of HiVelSCs",
          "label": "tab:origin"
        }
      ],
      "columns": [
        {
          "name": "Class",
          "meaning": "Origin class: HVS, HRS, RS, or OUT"
        },
        {
          "name": "Pgc",
          "meaning": "Probability of ejection from the Galactic Center threshold"
        },
        {
          "name": "PMW",
          "meaning": "Probability of ejection from the Galactic disk threshold"
        },
        {
          "name": "Pub",
          "meaning": "Unbound probability threshold"
        }
      ],
      "evidence": "Table in Section 4 defines the criteria used to classify 591 HiVelSCs into four origin types.",
      "comments": "Methodological table defining classification thresholds."
    },
    {
      "id": "table-005",
      "kind": "latex_table",
      "asset_type": "summary_table",
      "role_in_paper": "Tab:strict_criteria — Results of applying progressively more conservative selection criteria: number of HiVelSCs remaining and unbound counts.",
      "source_refs": [
        {
          "path": "literature/2011.10206/arxiv_source/LAMOST_II_HVS.tex",
          "start_line": 786,
          "end_line": 808,
          "caption": "The results using more stringent selection criteria",
          "label": "tab:strict_criteria"
        }
      ],
      "columns": [
        {
          "name": "Criteria",
          "meaning": "Selection criteria applied"
        },
        {
          "name": "N1",
          "meaning": "Total number of HiVelSCs satisfying criteria"
        },
        {
          "name": "N2",
          "meaning": "Number unbound in Watkins+2019 with Pub≥50%"
        },
        {
          "name": "N3",
          "meaning": "Number unbound in Xue+2008 with Pub≥50%"
        },
        {
          "name": "N4",
          "meaning": "Number bound in Xue+2008 with Pub<50%"
        },
        {
          "name": "Maximum V_GC",
          "meaning": "Maximum Galactocentric velocity among selected HiVelSCs (km/s)"
        }
      ],
      "evidence": "Table in Section 5.2 shows how stricter astrometric and velocity-precision cuts reduce the sample from 591 to 92 conservative candidates.",
      "comments": "Five-row summary table for sensitivity analysis."
    },
    {
      "id": "table-006",
      "kind": "latex_table",
      "asset_type": "object_measurement_table",
      "role_in_paper": "Tab:vesc (Appendix) — Escape velocities at each star's position under seven Galactic potential models, for the 20 fastest HiVelSCs.",
      "source_refs": [
        {
          "path": "literature/2011.10206/arxiv_source/LAMOST_II_HVS.tex",
          "start_line": 927,
          "end_line": 987,
          "caption": "Escape velocities of the 20 fastest HiVelSCs in the seven Galactic potential models",
          "label": "tab:vesc"
        }
      ],
      "columns": [
        {
          "name": "ID",
          "meaning": "High velocity star identifier"
        },
        {
          "name": "r_GC",
          "meaning": "Galactocentric distance (kpc)"
        },
        {
          "name": "V_GC",
          "meaning": "Galactocentric total velocity (km/s)"
        },
        {
          "name": "Vesc(W)",
          "meaning": "Escape velocity in Watkins+2019 potential (km/s)"
        },
        {
          "name": "Vesc(G)",
          "meaning": "Escape velocity in Gnedin+2005 potential (km/s)"
        },
        {
          "name": "Vesc(Ke)",
          "meaning": "Escape velocity in Kenyon+2014 potential (km/s)"
        },
        {
          "name": "Vesc(Ko)",
          "meaning": "Escape velocity in Koposov+2010 potential (km/s)"
        },
        {
          "name": "Vesc(P)",
          "meaning": "Escape velocity in Paczynski+1990 potential (km/s)"
        },
        {
          "name": "Vesc(M)",
          "meaning": "Escape velocity in MWPotential2014 (km/s)"
        },
        {
          "name": "Vesc(X)",
          "meaning": "Escape velocity in Xue+2008 potential (km/s)"
        }
      ],
      "evidence": "Appendix Table A1 lists escape velocities computed for the 20 fastest candidates across all seven potential models used in the study.",
      "comments": "Appendix table."
    },
    {
      "id": "table-007",
      "kind": "latex_table",
      "asset_type": "object_measurement_table",
      "role_in_paper": "Tab:unbound (Appendix) — Unbound probabilities Pgc, PMW, and Pub under seven potential models for the 20 fastest HiVelSCs, plus origin classification.",
      "source_refs": [
        {
          "path": "literature/2011.10206/arxiv_source/LAMOST_II_HVS.tex",
          "start_line": 991,
          "end_line": 1053,
          "caption": "Unbound probabilities of the 20 fastest HiVelSCs in the seven potential models",
          "label": "tab:unbound"
        }
      ],
      "columns": [
        {
          "name": "ID",
          "meaning": "High velocity star identifier"
        },
        {
          "name": "Pgc",
          "meaning": "Probability of ejection from the Galactic Center"
        },
        {
          "name": "PMW",
          "meaning": "Probability of ejection from the Galactic disk"
        },
        {
          "name": "Pub(W)–Pub(X)",
          "meaning": "Unbound probability under each of seven potential models"
        },
        {
          "name": "Origin_Class",
          "meaning": "Origin classification (HVS, HRS, RS, OUT)"
        }
      ],
      "evidence": "Appendix Table A2 presents ejection and unbound probabilities for the 20 fastest candidates, with origin classification in the last column.",
      "comments": "Appendix table."
    },
    {
      "id": "table-008",
      "kind": "latex_table",
      "asset_type": "object_measurement_table",
      "role_in_paper": "Tab:atmospheric (Appendix) — Atmospheric parameters (Teff, log g, [Fe/H]) from LASP and DD-Payne, plus [α/Fe] from DD-Payne, for the 20 fastest HiVelSCs.",
      "source_refs": [
        {
          "path": "literature/2011.10206/arxiv_source/LAMOST_II_HVS.tex",
          "start_line": 1056,
          "end_line": 1116,
          "caption": "Atmospheric parameters for the 20 fastest HiVelSCs",
          "label": "tab:atmospheric"
        }
      ],
      "columns": [
        {
          "name": "ID",
          "meaning": "High velocity star identifier"
        },
        {
          "name": "Teff_LASP",
          "meaning": "Effective temperature from LASP (K)"
        },
        {
          "name": "log_g_LASP",
          "meaning": "Surface gravity from LASP (dex)"
        },
        {
          "name": "[Fe/H]_LASP",
          "meaning": "Metallicity from LASP (dex)"
        },
        {
          "name": "Teff_DD-Payne",
          "meaning": "Effective temperature from DD-Payne (K)"
        },
        {
          "name": "log_g_DD-Payne",
          "meaning": "Surface gravity from DD-Payne (dex)"
        },
        {
          "name": "[Fe/H]_DD-Payne",
          "meaning": "Metallicity from DD-Payne (dex)"
        },
        {
          "name": "[α/Fe]_DD-Payne",
          "meaning": "Alpha-element abundance from DD-Payne (dex)"
        }
      ],
      "evidence": "Appendix Table A3 shows atmospheric parameters from two independent pipelines (LASP and DD-Payne) for the 20 fastest candidates.",
      "comments": "Appendix table."
    },
    {
      "id": "table-009",
      "kind": "latex_table",
      "asset_type": "data_dictionary",
      "role_in_paper": "Tab:general_catalog (Appendix) — Column-by-column description of the full 93-column HiVelSC catalog, specifying name, units, and description for each field.",
      "source_refs": [
        {
          "path": "literature/2011.10206/arxiv_source/LAMOST_II_HVS.tex",
          "start_line": 1159,
          "end_line": 1278,
          "caption": "Description of our HiVelSCs catalog",
          "label": "tab:general_catalog"
        }
      ],
      "columns": [
        {
          "name": "Column",
          "meaning": "Column index (1–93)"
        },
        {
          "name": "Name",
          "meaning": "Column name in the catalog"
        },
        {
          "name": "Units",
          "meaning": "Physical units"
        },
        {
          "name": "Description",
          "meaning": "Explanation of the column content and data provenance"
        }
      ],
      "evidence": "Appendix Table A4 is a 93-row data dictionary documenting every column of the LAMOSTDR7-GAIADR2-HiVelSC catalog, with superscripts indicating LAMOST, Gaia, or derived provenance.",
      "comments": "Data dictionary for the external CSV catalog."
    }
  ],
  "external_resources": [
    {
      "id": "resource-001",
      "kind": "external_url",
      "url": "http://paperdata.china-vo.org/LYB/lamostdr7_gaiadr2_hvs_591.csv",
      "local_path": "",
      "description": "Main data catalog: CSV file containing 93 columns for all 591 high-velocity star candidates, including LAMOST radial velocities and atmospheric parameters, Gaia DR2 astrometry and photometry, derived Galactocentric positions/velocities, escape velocities under seven potential models, unbound/ejection probabilities, and origin classification.",
      "source_refs": [
        {
          "path": "literature/2011.10206/arxiv_source/LAMOST_II_HVS.tex",
          "start_line": 106,
          "end_line": 106,
          "context": "A catalog for these 591 HiVelSCs, including radial velocities, atmospheric parameters, Gaia astrometric parameters, spatial positions, and velocities, etc., is  available at \\url{http://paperdata.china-vo.org/LYB/lamostdr7_gaiadr2_hvs_591.csv}."
        }
      ],
      "evidence": "Explicitly provided in the abstract as the primary data product URL; the appendix Table A4 (tab:general_catalog) documents all 93 columns of this catalog.",
      "comments": ""
    },
    {
      "id": "resource-002",
      "kind": "external_url",
      "url": "https://faststars.space/",
      "local_path": "",
      "description": "Open Fast Stars Catalog (OFSC), a community collection of 558 high-velocity star candidates from the literature, used by the authors for cross-matching and comparison with their new 591-candidate sample.",
      "source_refs": [
        {
          "path": "literature/2011.10206/arxiv_source/LAMOST_II_HVS.tex",
          "start_line": 302,
          "end_line": 302,
          "context": "only 14 of them were reported in the current version of the open fast stars catalog (OFSC) \\footnote{https://faststars.space/}"
        }
      ],
      "evidence": "Footnote in Section 2.4 citing the OFSC URL; the OFSC is used as a comparison sample throughout the paper.",
      "comments": ""
    },
    {
      "id": "resource-003",
      "kind": "external_url",
      "url": "http://dr7.lamost.org/",
      "local_path": "",
      "description": "LAMOST Data Release 7 access page — the spectroscopic survey providing radial velocities and atmospheric parameters for the 591 HiVelSCs.",
      "source_refs": [
        {
          "path": "literature/2011.10206/arxiv_source/LAMOST_II_HVS.tex",
          "start_line": 189,
          "end_line": 189,
          "context": "DR7 of Low-Resolution Spectroscopic Survey provided 10,608,416 low resolution spectra \\footnote{http://dr7.lamost.org/}"
        }
      ],
      "evidence": "Footnote in Section 2.1 referencing the LAMOST DR7 data release URL.",
      "comments": "Survey archive URL; the underlying LAMOST spectra are publicly available here but are not the paper's direct data product."
    },
    {
      "id": "resource-004",
      "kind": "external_url",
      "url": "http://www.star.bris.ac.uk/~mbt/topcat/",
      "local_path": "",
      "description": "TOPCAT tool used for cross-matching LAMOST DR7 with Gaia DR2 within a 5-arcsec radius to produce the LAMOST-Gaia input catalog.",
      "source_refs": [
        {
          "path": "literature/2011.10206/arxiv_source/LAMOST_II_HVS.tex",
          "start_line": 270,
          "end_line": 270,
          "context": "Using the TOPCAT \\footnote{http://www.star.bris.ac.uk/~mbt/topcat/}, cross-match of LAMOST DR7 with Gaia DR2 were performed with a radius of 5 arc sec"
        }
      ],
      "evidence": "Footnote in Section 2.3 describing the cross-match tool.",
      "comments": "Software tool URL, not a data product."
    }
  ]
}
